[
  {
    "id": 20,
    "pid": null,
    "type": 1,
    "name": "区域",
    "list": [],
    "listp": [
      {
        "id": 12,
        "signpid": null,
        "signid": 20,
        "signname": "中控楼",
        "signpoint": "10",
        "pointx": 324,
        "pointy": 619.8,
        "imgh": 907.8,
        "imgw": 1534.2,
        "cname": "区域",
        "pname": null,
        "longitude": 109.53833937544063,
        "latitude": 38.27461818001419
      },
      {
        "id": 13,
        "signpid": null,
        "signid": 20,
        "signname": "维修工房",
        "signpoint": "8",
        "pointx": 577,
        "pointy": 649.8,
        "imgh": 907.8,
        "imgw": 1534.2,
        "cname": "区域",
        "pname": null,
        "longitude": 109.53930531516907,
        "latitude": 38.274536444306484
      },
      {
        "id": 14,
        "signpid": null,
        "signid": 20,
        "signname": "应急库房",
        "signpoint": "8",
        "pointx": 535,
        "pointy": 663.8,
        "imgh": 907.8,
        "imgw": 1534.2,
        "cname": "区域",
        "pname": null,
        "longitude": 109.53914564201324,
        "latitude": 38.27449292165747
      },
      {
        "id": 15,
        "signpid": null,
        "signid": 20,
        "signname": "消防泵房",
        "signpoint": "8",
        "pointx": 679,
        "pointy": 618.8,
        "imgh": 907.8,
        "imgw": 1534.2,
        "cname": "区域",
        "pname": null,
        "longitude": 109.53969320038854,
        "latitude": 38.27463311834709
      },
      {
        "id": 16,
        "signpid": null,
        "signid": 20,
        "signname": "空氮站",
        "signpoint": "7",
        "pointx": 760.25,
        "pointy": 597.05,
        "imgh": 907.8,
        "imgw": 1534.2,
        "cname": "区域",
        "pname": null,
        "longitude": 109.54000228311965,
        "latitude": 38.27470127159892
      },
      {
        "id": 17,
        "signpid": null,
        "signid": 20,
        "signname": "锅炉房",
        "signpoint": "5",
        "pointx": 646.5,
        "pointy": 465.29999999999995,
        "imgh": 907.8,
        "imgw": 1534.2,
        "cname": "区域",
        "pname": null,
        "longitude": 109.53956375214003,
        "latitude": 38.27509374498337
      },
      {
        "id": 18,
        "signpid": null,
        "signid": 20,
        "signname": "回注间",
        "signpoint": "5",
        "pointx": 741.5,
        "pointy": 407.29999999999995,
        "imgh": 907.8,
        "imgw": 1534.2,
        "cname": "区域",
        "pname": null,
        "longitude": 109.53992397351512,
        "latitude": 38.275271398168286
      },
      {
        "id": 19,
        "signpid": null,
        "signid": 20,
        "signname": "低压配电室",
        "signpoint": "5",
        "pointx": 738,
        "pointy": 457.79999999999995,
        "imgh": 907.8,
        "imgw": 1534.2,
        "cname": "区域",
        "pname": null,
        "longitude": 109.53991243610581,
        "latitude": 38.27511937955322
      },
      {
        "id": 20,
        "signpid": null,
        "signid": 20,
        "signname": "循环水泵房",
        "signpoint": "5",
        "pointx": 617,
        "pointy": 425.29999999999995,
        "imgh": 907.8,
        "imgw": 1534.2,
        "cname": "区域",
        "pname": null,
        "longitude": 109.53944981414388,
        "latitude": 38.27521307120158
      },
      {
        "id": 21,
        "signpid": null,
        "signid": 20,
        "signname": "甲醇/凝析油/原料水罐区",
        "signpoint": "6",
        "pointx": 503.5,
        "pointy": 386.79999999999995,
        "imgh": 907.8,
        "imgw": 1534.2,
        "cname": "区域",
        "pname": null,
        "longitude": 109.53901557976431,
        "latitude": 38.27532506254304
      },
      {
        "id": 22,
        "signpid": null,
        "signid": 20,
        "signname": "甲醇回收装置区",
        "signpoint": "8",
        "pointx": 498,
        "pointy": 467.79999999999995,
        "imgh": 907.8,
        "imgw": 1534.2,
        "cname": "区域",
        "pname": null,
        "longitude": 109.538997508449,
        "latitude": 38.27508123453151
      },
      {
        "id": 23,
        "signpid": null,
        "signid": 20,
        "signname": "脱水脱氢装置区",
        "signpoint": "5",
        "pointx": 321,
        "pointy": 448.79999999999995,
        "imgh": 907.8,
        "imgw": 1534.2,
        "cname": "区域",
        "pname": null,
        "longitude": 109.53832180371184,
        "latitude": 38.275132437006725
      },
      {
        "id": 24,
        "signpid": null,
        "signid": 20,
        "signname": "丙烷压缩机房",
        "signpoint": "8",
        "pointx": 180.5,
        "pointy": 475.79999999999995,
        "imgh": 907.8,
        "imgw": 1534.2,
        "cname": "区域",
        "pname": null,
        "longitude": 109.53778694792818,
        "latitude": 38.275046500868356
      },
      {
        "id": 25,
        "signpid": null,
        "signid": 20,
        "signname": "凝析油罐区",
        "signpoint": "5",
        "pointx": 347.5,
        "pointy": 256.29999999999995,
        "imgh": 907.8,
        "imgw": 1534.2,
        "cname": "区域",
        "pname": null,
        "longitude": 109.53841596509577,
        "latitude": 38.27571235611722
      },
      {
        "id": 26,
        "signpid": null,
        "signid": 20,
        "signname": "甲醇/原料水罐区",
        "signpoint": "5",
        "pointx": 512.25,
        "pointy": 249.79999999999995,
        "imgh": 907.8,
        "imgw": 1534.2,
        "cname": "区域",
        "pname": null,
        "longitude": 109.53904403788114,
        "latitude": 38.275737444440296
      },
      {
        "id": 27,
        "signpid": null,
        "signid": 20,
        "signname": "食堂",
        "signpoint": "10",
        "pointx": 164.5,
        "pointy": 742.3,
        "imgh": 907.8,
        "imgw": 1534.2,
        "cname": "区域",
        "pname": null,
        "longitude": 109.5377354833449,
        "latitude": 38.27424434703713
      },
      {
        "id": 28,
        "signpid": null,
        "signid": 20,
        "signname": "10KV变配电室",
        "signpoint": "8",
        "pointx": 154.5,
        "pointy": 591.8,
        "imgh": 907.8,
        "imgw": 1534.2,
        "cname": "区域",
        "pname": null,
        "longitude": 109.53769195073053,
        "latitude": 38.27469670600377
      },
      {
        "id": 29,
        "signpid": null,
        "signid": 20,
        "signname": "装卸车区",
        "signpoint": "5",
        "pointx": 107.90625,
        "pointy": 277.08124999999995,
        "imgh": 907.8,
        "imgw": 1534.2,
        "cname": "区域",
        "pname": null,
        "longitude": 109.53750297327832,
        "latitude": 38.27564179539054
      },
      {
        "id": 30,
        "signpid": null,
        "signid": 20,
        "signname": "回注井",
        "signpoint": "3",
        "pointx": 819,
        "pointy": 251.29999999999995,
        "imgh": 907.8,
        "imgw": 1534.2,
        "cname": "区域",
        "pname": null,
        "longitude": 109.54021394180047,
        "latitude": 38.27574324139696
      },
      {
        "id": 31,
        "signpid": null,
        "signid": 20,
        "signname": "进站区",
        "signpoint": "5",
        "pointx": 874,
        "pointy": 477.79999999999995,
        "imgh": 907.8,
        "imgw": 1534.2,
        "cname": "区域",
        "pname": null,
        "longitude": 109.54043181530659,
        "latitude": 38.27506379126126
      },
      {
        "id": 32,
        "signpid": null,
        "signid": 20,
        "signname": "陕京一线外输区",
        "signpoint": "5",
        "pointx": 1072,
        "pointy": 430.29999999999995,
        "imgh": 907.8,
        "imgw": 1534.2,
        "cname": "区域",
        "pname": null,
        "longitude": 109.54118522344173,
        "latitude": 38.27521332256587
      },
      {
        "id": 33,
        "signpid": null,
        "signid": 20,
        "signname": "集气区",
        "signpoint": "5",
        "pointx": 1202,
        "pointy": 402.79999999999995,
        "imgh": 907.8,
        "imgw": 1534.2,
        "cname": "区域",
        "pname": null,
        "longitude": 109.54168001752937,
        "latitude": 38.27530040980369
      },
      {
        "id": 34,
        "signpid": null,
        "signid": 20,
        "signname": "进站区东线",
        "signpoint": "5",
        "pointx": 1427.5,
        "pointy": 322.79999999999995,
        "imgh": 907.8,
        "imgw": 1534.2,
        "cname": "区域",
        "pname": null,
        "longitude": 109.54253713702302,
        "latitude": 38.27554862335746
      },
      {
        "id": 35,
        "signpid": null,
        "signid": 20,
        "signname": "陕京二线外输区",
        "signpoint": "5",
        "pointx": 1327,
        "pointy": 188.29999999999995,
        "imgh": 907.8,
        "imgw": 1534.2,
        "cname": "区域",
        "pname": null,
        "longitude": 109.54214903887525,
        "latitude": 38.27594981386737
      },
      {
        "id": 36,
        "signpid": null,
        "signid": 20,
        "signname": "渗滤池",
        "signpoint": "5",
        "pointx": 700.5,
        "pointy": 220.29999999999995,
        "imgh": 907.8,
        "imgw": 1534.2,
        "cname": "区域",
        "pname": null,
        "longitude": 109.53976090784718,
        "latitude": 38.27583250515154
      }
    ]
  }
]